atacworks/__init__.py
atacworks/dl4atac/__init__.py
atacworks/dl4atac/custom_losses.py
atacworks/dl4atac/dataset.py
atacworks/dl4atac/evaluate.py
atacworks/dl4atac/infer.py
atacworks/dl4atac/layers.py
atacworks/dl4atac/losses.py
atacworks/dl4atac/metrics.py
atacworks/dl4atac/train.py
atacworks/dl4atac/utils.py
atacworks/dl4atac/models/model_utils.py
atacworks/dl4atac/models/models.py
atacworks/io/__init__.py
atacworks/io/bedgraphio.py
atacworks/io/bedio.py
atacworks/io/bigwigio.py
atacworks/io/bw2h5.py
atacworks/io/h5io.py
atacworks/io/peak2bw.py
atacworks-0.3.4.data/data/configs/infer_config.yaml
atacworks-0.3.4.data/data/configs/model_structure.yaml
atacworks-0.3.4.data/data/configs/train_config.yaml
atacworks-0.3.4.data/data/reference/hg19.auto.sizes
atacworks-0.3.4.data/data/reference/hg19.chrom.sizes
atacworks-0.3.4.data/data/reference/hg38.auto.sizes
atacworks-0.3.4.data/data/reference/hg38.chrom.sizes
ci/checks/check_copyright.py
ci/release/update_configuration.py
configs/infer_config.yaml
configs/model_structure.yaml
configs/train_config.yaml
data/reference/hg19.auto.sizes
data/reference/hg19.chrom.sizes
data/reference/hg38.auto.sizes
data/reference/hg38.chrom.sizes
docs/conf.py
scripts/calculate_baseline_metrics.py
scripts/cmd_args.py
scripts/main.py
scripts/peaksummary.py
scripts/worker.py
tests/test_metrics.py
tests/dl4atac/test_dataset.py
tests/io/test_bedgraphio.py
tests/io/test_bedio.py
tests/io/test_bigwigio.py
tests/io/test_h5io.py
tests/utils/verify_diff.py
atacworks-0.3.4.dist-info/LICENSE
atacworks-0.3.4.dist-info/METADATA
atacworks-0.3.4.dist-info/WHEEL
atacworks-0.3.4.dist-info/entry_points.txt
atacworks-0.3.4.dist-info/top_level.txt
atacworks-0.3.4.dist-info/RECORD
